{"protocols":{"api-version":3,"api-revision":"091015","version":1.0,"revision":"091015","total-protocols":6,"protocol":[{"id":441807,"accession":"P-GSE32672-1","name":"P-GSE32672-1","text":["ID_REF = ",{"br":null},"VALUE = MAS5",{"br":null},"ABS_CALL = ",{"br":null},"DETECTION P-VALUE = "],"type":"bioassay_data_transformation","performer":null,"hardware":null,"software":null,"standardpublicprotocol":null},{"id":441812,"accession":"P-GSE32672-2","name":"P-GSE32672-2","text":"Qiagen RNAeasy kit protocol","type":"nucleic_acid_extraction","performer":null,"hardware":null,"software":null,"standardpublicprotocol":null},{"id":441811,"accession":"P-GSE32672-3","name":"P-GSE32672-3","text":"Labelled using protocol described in manual \"Affymetrix GeneChip Expression Analysis Technical Manual\", One-Cycle target labelling","type":"labeling","performer":null,"hardware":null,"software":null,"standardpublicprotocol":null},{"id":441810,"accession":"P-GSE32672-4","name":"P-GSE32672-4","text":"Biotin Labelled cRNA using \"Affymetrix GeneChip Hybridization, Wash and Stain Kit\", according to guidelines set out by Affymetrix, Santa Clara, CA","type":"hybridization","performer":null,"hardware":null,"software":null,"standardpublicprotocol":null},{"id":441809,"accession":"P-GSE32672-5","name":"P-GSE32672-5","text":"Scanned according to guidelines set out by Affymetrix, Santa Clara, CA.","type":"image_aquisition","performer":null,"hardware":null,"software":null,"standardpublicprotocol":null},{"id":441808,"accession":"P-GSE32672-6","name":"P-GSE32672-6","text":"Raw data from the microarrays was normalized at probe-level using MAS5 algorithm. The detection calls (present, marginal, absent) for each probe set was obtained using the GCOS system","type":"feature_extraction","performer":null,"hardware":null,"software":null,"standardpublicprotocol":null}]}}