{"protocols":{"api-version":3,"api-revision":"091015","version":1.0,"revision":"091015","total-protocols":7,"protocol":[{"id":63,"accession":"Affymetrix:Protocol:ExpressionStat","name":"Affymetrix:Protocol:ExpressionStat","text":"Title: Affymetrix CHP Analysis (ExpressionStat). Description:","type":"bioassay_data_transformation","performer":null,"hardware":null,"software":"MicroArraySuite 5.0","standardpublicprotocol":1,"parameter":["Algorithm name","Algorithm version","Alpha1","Alpha2","Baseline file","Gamma1H","Gamma1L","Gamma2H","Gamma2L","Mask file","Normalization factor","Perturbation","Scale factor","Tau"]},{"id":57,"accession":"Affymetrix:Protocol:Hybridization-EukGE-WS2v4_450","name":"Affymetrix:Protocol:Hybridization-EukGE-WS2v4_450","text":"Title: Affymetrix EukGE-WS2v4_450 Hybridization. Description:","type":"hybridization","performer":null,"hardware":null,"software":"MicroArraySuite 5.0","standardpublicprotocol":1},{"id":125,"accession":"Affymetrix:Protocol:Hybridization-EukGE-WS2v5_450","name":"Affymetrix:Protocol:Hybridization-EukGE-WS2v5_450","text":"(Parameters: Extracted product = total_RNA, Amplification = none)","type":"hybridization","performer":null,"hardware":null,"software":"MicroArraySuite 5.0","standardpublicprotocol":1},{"id":77,"accession":"P-AFFY-2","name":"P-AFFY-2","text":"Labeling of samples was carried out according to the manufacturer’s standard protocol","type":"nucleic acid labeling protocol","performer":null,"hardware":null,"software":null,"standardpublicprotocol":1,"parameter":"Quantity of starting RNA (ug)"},{"id":51,"accession":"P-AFFY-6","name":"P-AFFY-6","text":"Title: Affymetrix CEL analysis. Description:","type":"feature_extraction","performer":null,"hardware":"418 [Affymetrix]","software":"MicroArraySuite 5.0","standardpublicprotocol":1},{"id":81046,"accession":"P-MEXP-134916","name":"P-MEXP-134916","text":"Seeds were germinated on sterile, solid Murashige and Skoog (MS) medium in plastic petri dishes. Seedlings were then transferred to pots containing a mixture of Huminsubstrat N3 and Vermiculit Nr.2 (2:1 v\/v) (purchased from a local supplier), and placed in a culture room with natural light (3000 lux). The photoperiod was 16 h and temperature was maintained at 23 °C. Single leaves were cut from the plants at a stage of approximately ten rosette leaves (>1 cm in length).","type":"grow","performer":null,"hardware":null,"software":null,"standardpublicprotocol":0,"parameter":["media","min temperature","start time","stop time"]},{"id":81045,"accession":"P-MEXP-135114","name":"P-MEXP-135114","text":"Total RNA was extracted and purified with an RNeasy Mini Kit (Qiagen, Hilden, Germany). RNA was quantified by spectrophotometry (Nanodrop ND-1000, Peqlab, Erlangen, Germany). Double-stranded cDNA was synthesized from 1 ug total RNA by using the one-cycle cDNA synthesis kit (GeneChip One-Cycle Target Labeling and Control Reagents, Affymetrix, High Wycombe, U.K.) ","type":"nucleic_acid_extraction","performer":null,"hardware":null,"software":null,"standardpublicprotocol":0,"parameter":["Amplification","Extracted product"]}]}}