{"protocols":{"api-version":3,"api-revision":"091015","version":1.0,"revision":"091015","total-protocols":6,"protocol":[{"id":1128316,"accession":"P-GSE18988-1","name":null,"text":["ID_REF = ",{"br":null},"VALUE = MAS5 normalized signal intensity",{"br":null},"ABS_CALL = present, marginal, absent calls",{"br":null},"DETECTION P-VALUE = p-value"],"type":"bioassay_data_transformation","performer":null,"hardware":null,"software":null,"standardpublicprotocol":null},{"id":1128321,"accession":"P-GSE18988-2","name":null,"text":"Qiagen RNeasy kit protocol","type":"nucleic_acid_extraction","performer":null,"hardware":null,"software":null,"standardpublicprotocol":null},{"id":1128320,"accession":"P-GSE18988-3","name":null,"text":"Labelled using protocol described in Affymetrix manual \"3' IVT Express Kit User Manual\"","type":"labeling","performer":null,"hardware":null,"software":null,"standardpublicprotocol":null},{"id":1128319,"accession":"P-GSE18988-4","name":null,"text":"Biotin Labelled cRNA using \"Affymetrix GeneChip Hybridization, Wash and Stain Kit\", according to guidelines set out by Affymetrix, Santa Clara, CA","type":"hybridization","performer":null,"hardware":null,"software":null,"standardpublicprotocol":null},{"id":1128317,"accession":"P-GSE18988-5","name":null,"text":"Scanned according to guidelines set out by Affymetrix, Santa Clara, CA.","type":"image_aquisition","performer":null,"hardware":null,"software":null,"standardpublicprotocol":null},{"id":1128318,"accession":"P-GSE18988-6","name":null,"text":"Raw data from the microarrays was normalized at probe-level using MAS5 algorithm. The detection calls (present, marginal, absent) for each probe set was obtained using the GCOS system","type":"feature_extraction","performer":null,"hardware":null,"software":null,"standardpublicprotocol":null}]}}