{"protocols":{"api-version":3,"api-revision":"091015","version":1.0,"revision":"091015","total-protocols":6,"protocol":[{"id":62,"accession":"Affymetrix:Protocol:Hybridization-Unknown","name":"Affymetrix:Protocol:Hybridization-Unknown","text":"Affymetrix Generic Hybridization","type":"hybridization protocol","performer":null,"hardware":null,"software":"MicroArraySuite 5.0","standardpublicprotocol":1},{"id":77,"accession":"P-AFFY-2","name":"P-AFFY-2","text":"Labeling of samples was carried out according to the manufacturer’s standard protocol","type":"nucleic acid labeling protocol","performer":null,"hardware":null,"software":null,"standardpublicprotocol":1,"parameter":"Quantity of starting RNA (ug)"},{"id":51,"accession":"P-AFFY-6","name":"P-AFFY-6","text":"Title: Affymetrix CEL analysis. Description:","type":"feature_extraction","performer":null,"hardware":"418 [Affymetrix]","software":"MicroArraySuite 5.0","standardpublicprotocol":1},{"id":512807,"accession":"P-CAGE-25383","name":"P-CAGE-25383","text":"Samples were vacuum-filtered, immediately frozen in liquid nitrogen, ground and stored at -80.","type":"specified_biomaterial_action","performer":null,"hardware":null,"software":null,"standardpublicprotocol":null},{"id":512809,"accession":"P-CAGE-25384","name":"P-CAGE-25384","text":"Total RNA was isolated from 50 mg ground cells using TRIzol (Invitrogen) according to the manufacturer’s instructions.","type":"nucleic_acid_extraction","performer":null,"hardware":null,"software":null,"standardpublicprotocol":null,"parameter":["Amplification","Extracted product"]},{"id":512808,"accession":"P-CAGE-25473","name":"P-CAGE-25473","text":"Raw data were transformed using the robust multiarray analysis algorithm (rma) as implemented in the BioConductor affy package. Default background correction, normalization, and summary expression methods were used.","type":"bioassay_data_transformation","performer":null,"hardware":null,"software":null,"standardpublicprotocol":null}]}}