{"protocols":{"api-version":3,"api-revision":"091015","version":1.0,"revision":"091015","total-protocols":6,"protocol":[{"id":63,"accession":"Affymetrix:Protocol:ExpressionStat","name":"Affymetrix:Protocol:ExpressionStat","text":"Title: Affymetrix CHP Analysis (ExpressionStat). Description:","type":"bioassay_data_transformation","performer":null,"hardware":null,"software":"MicroArraySuite 5.0","standardpublicprotocol":1,"parameter":["Algorithm name","Algorithm version","Alpha1","Alpha2","Baseline file","Gamma1H","Gamma1L","Gamma2H","Gamma2L","Mask file","Normalization factor","Perturbation","Scale factor","Tau"]},{"id":57,"accession":"Affymetrix:Protocol:Hybridization-EukGE-WS2v4_450","name":"Affymetrix:Protocol:Hybridization-EukGE-WS2v4_450","text":"Title: Affymetrix EukGE-WS2v4_450 Hybridization. Description:","type":"hybridization","performer":null,"hardware":null,"software":"MicroArraySuite 5.0","standardpublicprotocol":1},{"id":51,"accession":"P-AFFY-6","name":"P-AFFY-6","text":"Title: Affymetrix CEL analysis. Description:","type":"feature_extraction","performer":null,"hardware":"418 [Affymetrix]","software":"MicroArraySuite 5.0","standardpublicprotocol":1},{"id":1015624,"accession":"P-TABM-40","name":"P-TABM-40","text":"Plants were grown on soil for 21 days under short day conditions (8 hr light\/16 hr darkness) at 23C and 65% relative humidity. Leaves #1, 3, and 5 of 10 plants were pooled per replicate; plants of all replicates were grown at the same timepoint.","type":"grow","performer":null,"hardware":null,"software":null,"standardpublicprotocol":null,"parameter":"photoperiod"},{"id":1015623,"accession":"P-TABM-41","name":"P-TABM-41","text":["A pdf of the protocol 'Probe preparation (Development)' can be downloaded at ",{"a":{"href":"http:\/\/www.weigelworld.org\/resources\/microarray\/AtGenExpress\/;","target":"_blank","$":"http:\/\/www.weigelworld.org\/resources\/microarray\/AtGenExpress\/;"}}," also at TAIR ",{"a":{"href":"http:\/\/www.arabidopsis.org","target":"_blank","$":"http:\/\/www.arabidopsis.org"}}," Protocol:501712557."],"type":"nucleic_acid_extraction","performer":null,"hardware":null,"software":null,"standardpublicprotocol":null},{"id":1015622,"accession":"P-TABM-43","name":"P-TABM-43","text":["A pdf of the protocol 'Probe preparation (Development)' can be downloaded at ",{"a":{"href":"http:\/\/www.weigelworld.org\/resources\/microarray\/AtGenExpress\/;","target":"_blank","$":"http:\/\/www.weigelworld.org\/resources\/microarray\/AtGenExpress\/;"}}," also at TAIR ",{"a":{"href":"http:\/\/www.arabidopsis.org","target":"_blank","$":"http:\/\/www.arabidopsis.org"}}," Protocol:501712557."],"type":"labeling","performer":null,"hardware":null,"software":null,"standardpublicprotocol":null}]}}