{"experiment":{"api-version":3,"api-revision":"091015","version":1.0,"revision":"091015","accession":"E-GEOD-10522","sample":[{"assay":{"name":"short 10A"},"characteristic":[{"category":"Organism","value":"Arabidopsis thaliana"},{"category":"Age","value":"4-5","unit":"weeks"},{"category":"OrganismPart","value":"rosette"},{"category":"Ecotype","value":"Col-0"}],"extract":{"name":"GSE10522GSM265850 extract"},"file":[{"type":"data","name":"GSM265850.CEL","url":"ftp:\/\/ftp.ebi.ac.uk\/pub\/databases\/microarray\/data\/experiment\/GEOD\/E-GEOD-10522\/E-GEOD-10522.raw.1.zip\/GSM265850.CEL","comment":{"name":"ArrayExpress FTP file","value":"ftp:\/\/ftp.ebi.ac.uk\/pub\/databases\/microarray\/data\/experiment\/GEOD\/E-GEOD-10522\/E-GEOD-10522.raw.1.zip"}},{"type":"derived data matrix","name":"E-GEOD-10522-processed-data-1605344270.txt","url":"ftp:\/\/ftp.ebi.ac.uk\/pub\/databases\/microarray\/data\/experiment\/GEOD\/E-GEOD-10522\/E-GEOD-10522.processed.1.zip\/E-GEOD-10522-processed-data-1605344270.txt","comment":{"name":"Derived ArrayExpress FTP file","value":"ftp:\/\/ftp.ebi.ac.uk\/pub\/databases\/microarray\/data\/experiment\/GEOD\/E-GEOD-10522\/E-GEOD-10522.processed.1.zip"}}],"labeled-extract":{"name":"GSE10522GSM265850 LE","label":"biotin"},"scan":{"name":"short 10A"},"source":{"name":"GSE10522GSM265850"},"variable":[{"name":"TREATMENT TIME","value":6,"unit":"hours"},{"name":"TEMPERATURE","value":10,"unit":"degree_C"}]},{"assay":{"name":"short 10B"},"characteristic":[{"category":"Organism","value":"Arabidopsis thaliana"},{"category":"Age","value":"4-5","unit":"weeks"},{"category":"OrganismPart","value":"rosette"},{"category":"Ecotype","value":"Col-0"}],"extract":{"name":"GSE10522GSM265862 extract"},"file":[{"type":"data","name":"GSM265862.CEL","url":"ftp:\/\/ftp.ebi.ac.uk\/pub\/databases\/microarray\/data\/experiment\/GEOD\/E-GEOD-10522\/E-GEOD-10522.raw.1.zip\/GSM265862.CEL","comment":{"name":"ArrayExpress FTP file","value":"ftp:\/\/ftp.ebi.ac.uk\/pub\/databases\/microarray\/data\/experiment\/GEOD\/E-GEOD-10522\/E-GEOD-10522.raw.1.zip"}},{"type":"derived data matrix","name":"E-GEOD-10522-processed-data-1605344270.txt","url":"ftp:\/\/ftp.ebi.ac.uk\/pub\/databases\/microarray\/data\/experiment\/GEOD\/E-GEOD-10522\/E-GEOD-10522.processed.1.zip\/E-GEOD-10522-processed-data-1605344270.txt","comment":{"name":"Derived ArrayExpress FTP file","value":"ftp:\/\/ftp.ebi.ac.uk\/pub\/databases\/microarray\/data\/experiment\/GEOD\/E-GEOD-10522\/E-GEOD-10522.processed.1.zip"}}],"labeled-extract":{"name":"GSE10522GSM265862 LE","label":"biotin"},"scan":{"name":"short 10B"},"source":{"name":"GSE10522GSM265862"},"variable":[{"name":"TREATMENT TIME","value":6,"unit":"hours"},{"name":"TEMPERATURE","value":10,"unit":"degree_C"}]},{"assay":{"name":"long 10B"},"characteristic":[{"category":"Organism","value":"Arabidopsis thaliana"},{"category":"Age","value":"4-5","unit":"weeks"},{"category":"OrganismPart","value":"rosette"},{"category":"Ecotype","value":"Col-0"}],"extract":{"name":"GSE10522GSM265868 extract"},"file":[{"type":"data","name":"GSM265868.CEL","url":"ftp:\/\/ftp.ebi.ac.uk\/pub\/databases\/microarray\/data\/experiment\/GEOD\/E-GEOD-10522\/E-GEOD-10522.raw.1.zip\/GSM265868.CEL","comment":{"name":"ArrayExpress FTP file","value":"ftp:\/\/ftp.ebi.ac.uk\/pub\/databases\/microarray\/data\/experiment\/GEOD\/E-GEOD-10522\/E-GEOD-10522.raw.1.zip"}},{"type":"derived data matrix","name":"E-GEOD-10522-processed-data-1605344270.txt","url":"ftp:\/\/ftp.ebi.ac.uk\/pub\/databases\/microarray\/data\/experiment\/GEOD\/E-GEOD-10522\/E-GEOD-10522.processed.1.zip\/E-GEOD-10522-processed-data-1605344270.txt","comment":{"name":"Derived ArrayExpress FTP file","value":"ftp:\/\/ftp.ebi.ac.uk\/pub\/databases\/microarray\/data\/experiment\/GEOD\/E-GEOD-10522\/E-GEOD-10522.processed.1.zip"}}],"labeled-extract":{"name":"GSE10522GSM265868 LE","label":"biotin"},"scan":{"name":"long 10B"},"source":{"name":"GSE10522GSM265868"},"variable":[{"name":"TREATMENT TIME","value":78,"unit":"hours"},{"name":"TEMPERATURE","value":10,"unit":"degree_C"}]},{"assay":{"name":"long 10A"},"characteristic":[{"category":"Organism","value":"Arabidopsis thaliana"},{"category":"Age","value":"4-5","unit":"weeks"},{"category":"OrganismPart","value":"rosette"},{"category":"Ecotype","value":"Col-0"}],"extract":{"name":"GSE10522GSM265856 extract"},"file":[{"type":"data","name":"GSM265856.CEL","url":"ftp:\/\/ftp.ebi.ac.uk\/pub\/databases\/microarray\/data\/experiment\/GEOD\/E-GEOD-10522\/E-GEOD-10522.raw.1.zip\/GSM265856.CEL","comment":{"name":"ArrayExpress FTP file","value":"ftp:\/\/ftp.ebi.ac.uk\/pub\/databases\/microarray\/data\/experiment\/GEOD\/E-GEOD-10522\/E-GEOD-10522.raw.1.zip"}},{"type":"derived data matrix","name":"E-GEOD-10522-processed-data-1605344270.txt","url":"ftp:\/\/ftp.ebi.ac.uk\/pub\/databases\/microarray\/data\/experiment\/GEOD\/E-GEOD-10522\/E-GEOD-10522.processed.1.zip\/E-GEOD-10522-processed-data-1605344270.txt","comment":{"name":"Derived ArrayExpress FTP file","value":"ftp:\/\/ftp.ebi.ac.uk\/pub\/databases\/microarray\/data\/experiment\/GEOD\/E-GEOD-10522\/E-GEOD-10522.processed.1.zip"}}],"labeled-extract":{"name":"GSE10522GSM265856 LE","label":"biotin"},"scan":{"name":"long 10A"},"source":{"name":"GSE10522GSM265856"},"variable":[{"name":"TREATMENT TIME","value":78,"unit":"hours"},{"name":"TEMPERATURE","value":10,"unit":"degree_C"}]},{"assay":{"name":"short 12B"},"characteristic":[{"category":"Organism","value":"Arabidopsis thaliana"},{"category":"Age","value":"4-5","unit":"weeks"},{"category":"OrganismPart","value":"rosette"},{"category":"Ecotype","value":"Col-0"}],"extract":{"name":"GSE10522GSM265861 extract"},"file":[{"type":"data","name":"GSM265861.CEL","url":"ftp:\/\/ftp.ebi.ac.uk\/pub\/databases\/microarray\/data\/experiment\/GEOD\/E-GEOD-10522\/E-GEOD-10522.raw.1.zip\/GSM265861.CEL","comment":{"name":"ArrayExpress FTP file","value":"ftp:\/\/ftp.ebi.ac.uk\/pub\/databases\/microarray\/data\/experiment\/GEOD\/E-GEOD-10522\/E-GEOD-10522.raw.1.zip"}},{"type":"derived data matrix","name":"E-GEOD-10522-processed-data-1605344270.txt","url":"ftp:\/\/ftp.ebi.ac.uk\/pub\/databases\/microarray\/data\/experiment\/GEOD\/E-GEOD-10522\/E-GEOD-10522.processed.1.zip\/E-GEOD-10522-processed-data-1605344270.txt","comment":{"name":"Derived ArrayExpress FTP file","value":"ftp:\/\/ftp.ebi.ac.uk\/pub\/databases\/microarray\/data\/experiment\/GEOD\/E-GEOD-10522\/E-GEOD-10522.processed.1.zip"}}],"labeled-extract":{"name":"GSE10522GSM265861 LE","label":"biotin"},"scan":{"name":"short 12B"},"source":{"name":"GSE10522GSM265861"},"variable":[{"name":"TREATMENT TIME","value":6,"unit":"hours"},{"name":"TEMPERATURE","value":12,"unit":"degree_C"}]},{"assay":{"name":"short 12A"},"characteristic":[{"category":"Organism","value":"Arabidopsis thaliana"},{"category":"Age","value":"4-5","unit":"weeks"},{"category":"OrganismPart","value":"rosette"},{"category":"Ecotype","value":"Col-0"}],"extract":{"name":"GSE10522GSM265849 extract"},"file":[{"type":"data","name":"GSM265849.CEL","url":"ftp:\/\/ftp.ebi.ac.uk\/pub\/databases\/microarray\/data\/experiment\/GEOD\/E-GEOD-10522\/E-GEOD-10522.raw.1.zip\/GSM265849.CEL","comment":{"name":"ArrayExpress FTP file","value":"ftp:\/\/ftp.ebi.ac.uk\/pub\/databases\/microarray\/data\/experiment\/GEOD\/E-GEOD-10522\/E-GEOD-10522.raw.1.zip"}},{"type":"derived data matrix","name":"E-GEOD-10522-processed-data-1605344270.txt","url":"ftp:\/\/ftp.ebi.ac.uk\/pub\/databases\/microarray\/data\/experiment\/GEOD\/E-GEOD-10522\/E-GEOD-10522.processed.1.zip\/E-GEOD-10522-processed-data-1605344270.txt","comment":{"name":"Derived ArrayExpress FTP file","value":"ftp:\/\/ftp.ebi.ac.uk\/pub\/databases\/microarray\/data\/experiment\/GEOD\/E-GEOD-10522\/E-GEOD-10522.processed.1.zip"}}],"labeled-extract":{"name":"GSE10522GSM265849 LE","label":"biotin"},"scan":{"name":"short 12A"},"source":{"name":"GSE10522GSM265849"},"variable":[{"name":"TREATMENT TIME","value":6,"unit":"hours"},{"name":"TEMPERATURE","value":12,"unit":"degree_C"}]},{"assay":{"name":"long 12A"},"characteristic":[{"category":"Organism","value":"Arabidopsis thaliana"},{"category":"Age","value":"4-5","unit":"weeks"},{"category":"OrganismPart","value":"rosette"},{"category":"Ecotype","value":"Col-0"}],"extract":{"name":"GSE10522GSM265855 extract"},"file":[{"type":"data","name":"GSM265855.CEL","url":"ftp:\/\/ftp.ebi.ac.uk\/pub\/databases\/microarray\/data\/experiment\/GEOD\/E-GEOD-10522\/E-GEOD-10522.raw.1.zip\/GSM265855.CEL","comment":{"name":"ArrayExpress FTP file","value":"ftp:\/\/ftp.ebi.ac.uk\/pub\/databases\/microarray\/data\/experiment\/GEOD\/E-GEOD-10522\/E-GEOD-10522.raw.1.zip"}},{"type":"derived data matrix","name":"E-GEOD-10522-processed-data-1605344270.txt","url":"ftp:\/\/ftp.ebi.ac.uk\/pub\/databases\/microarray\/data\/experiment\/GEOD\/E-GEOD-10522\/E-GEOD-10522.processed.1.zip\/E-GEOD-10522-processed-data-1605344270.txt","comment":{"name":"Derived ArrayExpress FTP file","value":"ftp:\/\/ftp.ebi.ac.uk\/pub\/databases\/microarray\/data\/experiment\/GEOD\/E-GEOD-10522\/E-GEOD-10522.processed.1.zip"}}],"labeled-extract":{"name":"GSE10522GSM265855 LE","label":"biotin"},"scan":{"name":"long 12A"},"source":{"name":"GSE10522GSM265855"},"variable":[{"name":"TREATMENT TIME","value":78,"unit":"hours"},{"name":"TEMPERATURE","value":12,"unit":"degree_C"}]},{"assay":{"name":"long 12B"},"characteristic":[{"category":"Organism","value":"Arabidopsis thaliana"},{"category":"Age","value":"4-5","unit":"weeks"},{"category":"OrganismPart","value":"rosette"},{"category":"Ecotype","value":"Col-0"}],"extract":{"name":"GSE10522GSM265867 extract"},"file":[{"type":"data","name":"GSM265867.CEL","url":"ftp:\/\/ftp.ebi.ac.uk\/pub\/databases\/microarray\/data\/experiment\/GEOD\/E-GEOD-10522\/E-GEOD-10522.raw.1.zip\/GSM265867.CEL","comment":{"name":"ArrayExpress FTP file","value":"ftp:\/\/ftp.ebi.ac.uk\/pub\/databases\/microarray\/data\/experiment\/GEOD\/E-GEOD-10522\/E-GEOD-10522.raw.1.zip"}},{"type":"derived data matrix","name":"E-GEOD-10522-processed-data-1605344270.txt","url":"ftp:\/\/ftp.ebi.ac.uk\/pub\/databases\/microarray\/data\/experiment\/GEOD\/E-GEOD-10522\/E-GEOD-10522.processed.1.zip\/E-GEOD-10522-processed-data-1605344270.txt","comment":{"name":"Derived ArrayExpress FTP file","value":"ftp:\/\/ftp.ebi.ac.uk\/pub\/databases\/microarray\/data\/experiment\/GEOD\/E-GEOD-10522\/E-GEOD-10522.processed.1.zip"}}],"labeled-extract":{"name":"GSE10522GSM265867 LE","label":"biotin"},"scan":{"name":"long 12B"},"source":{"name":"GSE10522GSM265867"},"variable":[{"name":"TREATMENT TIME","value":78,"unit":"hours"},{"name":"TEMPERATURE","value":12,"unit":"degree_C"}]},{"assay":{"name":"short 14B"},"characteristic":[{"category":"Organism","value":"Arabidopsis thaliana"},{"category":"Age","value":"4-5","unit":"weeks"},{"category":"OrganismPart","value":"rosette"},{"category":"Ecotype","value":"Col-0"}],"extract":{"name":"GSE10522GSM265860 extract"},"file":[{"type":"data","name":"GSM265860.CEL","url":"ftp:\/\/ftp.ebi.ac.uk\/pub\/databases\/microarray\/data\/experiment\/GEOD\/E-GEOD-10522\/E-GEOD-10522.raw.1.zip\/GSM265860.CEL","comment":{"name":"ArrayExpress FTP file","value":"ftp:\/\/ftp.ebi.ac.uk\/pub\/databases\/microarray\/data\/experiment\/GEOD\/E-GEOD-10522\/E-GEOD-10522.raw.1.zip"}},{"type":"derived data matrix","name":"E-GEOD-10522-processed-data-1605344270.txt","url":"ftp:\/\/ftp.ebi.ac.uk\/pub\/databases\/microarray\/data\/experiment\/GEOD\/E-GEOD-10522\/E-GEOD-10522.processed.1.zip\/E-GEOD-10522-processed-data-1605344270.txt","comment":{"name":"Derived ArrayExpress FTP file","value":"ftp:\/\/ftp.ebi.ac.uk\/pub\/databases\/microarray\/data\/experiment\/GEOD\/E-GEOD-10522\/E-GEOD-10522.processed.1.zip"}}],"labeled-extract":{"name":"GSE10522GSM265860 LE","label":"biotin"},"scan":{"name":"short 14B"},"source":{"name":"GSE10522GSM265860"},"variable":[{"name":"TREATMENT TIME","value":6,"unit":"hours"},{"name":"TEMPERATURE","value":14,"unit":"degree_C"}]},{"assay":{"name":"short 14A"},"characteristic":[{"category":"Organism","value":"Arabidopsis thaliana"},{"category":"Age","value":"4-5","unit":"weeks"},{"category":"OrganismPart","value":"rosette"},{"category":"Ecotype","value":"Col-0"}],"extract":{"name":"GSE10522GSM265848 extract"},"file":[{"type":"data","name":"GSM265848.CEL","url":"ftp:\/\/ftp.ebi.ac.uk\/pub\/databases\/microarray\/data\/experiment\/GEOD\/E-GEOD-10522\/E-GEOD-10522.raw.1.zip\/GSM265848.CEL","comment":{"name":"ArrayExpress FTP file","value":"ftp:\/\/ftp.ebi.ac.uk\/pub\/databases\/microarray\/data\/experiment\/GEOD\/E-GEOD-10522\/E-GEOD-10522.raw.1.zip"}},{"type":"derived data matrix","name":"E-GEOD-10522-processed-data-1605344270.txt","url":"ftp:\/\/ftp.ebi.ac.uk\/pub\/databases\/microarray\/data\/experiment\/GEOD\/E-GEOD-10522\/E-GEOD-10522.processed.1.zip\/E-GEOD-10522-processed-data-1605344270.txt","comment":{"name":"Derived ArrayExpress FTP file","value":"ftp:\/\/ftp.ebi.ac.uk\/pub\/databases\/microarray\/data\/experiment\/GEOD\/E-GEOD-10522\/E-GEOD-10522.processed.1.zip"}}],"labeled-extract":{"name":"GSE10522GSM265848 LE","label":"biotin"},"scan":{"name":"short 14A"},"source":{"name":"GSE10522GSM265848"},"variable":[{"name":"TREATMENT TIME","value":6,"unit":"hours"},{"name":"TEMPERATURE","value":14,"unit":"degree_C"}]},{"assay":{"name":"long 14B"},"characteristic":[{"category":"Organism","value":"Arabidopsis thaliana"},{"category":"Age","value":"4-5","unit":"weeks"},{"category":"OrganismPart","value":"rosette"},{"category":"Ecotype","value":"Col-0"}],"extract":{"name":"GSE10522GSM265866 extract"},"file":[{"type":"data","name":"GSM265866.CEL","url":"ftp:\/\/ftp.ebi.ac.uk\/pub\/databases\/microarray\/data\/experiment\/GEOD\/E-GEOD-10522\/E-GEOD-10522.raw.1.zip\/GSM265866.CEL","comment":{"name":"ArrayExpress FTP file","value":"ftp:\/\/ftp.ebi.ac.uk\/pub\/databases\/microarray\/data\/experiment\/GEOD\/E-GEOD-10522\/E-GEOD-10522.raw.1.zip"}},{"type":"derived data matrix","name":"E-GEOD-10522-processed-data-1605344270.txt","url":"ftp:\/\/ftp.ebi.ac.uk\/pub\/databases\/microarray\/data\/experiment\/GEOD\/E-GEOD-10522\/E-GEOD-10522.processed.1.zip\/E-GEOD-10522-processed-data-1605344270.txt","comment":{"name":"Derived ArrayExpress FTP file","value":"ftp:\/\/ftp.ebi.ac.uk\/pub\/databases\/microarray\/data\/experiment\/GEOD\/E-GEOD-10522\/E-GEOD-10522.processed.1.zip"}}],"labeled-extract":{"name":"GSE10522GSM265866 LE","label":"biotin"},"scan":{"name":"long 14B"},"source":{"name":"GSE10522GSM265866"},"variable":[{"name":"TREATMENT TIME","value":78,"unit":"hours"},{"name":"TEMPERATURE","value":14,"unit":"degree_C"}]},{"assay":{"name":"long 14A"},"characteristic":[{"category":"Organism","value":"Arabidopsis thaliana"},{"category":"Age","value":"4-5","unit":"weeks"},{"category":"OrganismPart","value":"rosette"},{"category":"Ecotype","value":"Col-0"}],"extract":{"name":"GSE10522GSM265854 extract"},"file":[{"type":"data","name":"GSM265854.CEL","url":"ftp:\/\/ftp.ebi.ac.uk\/pub\/databases\/microarray\/data\/experiment\/GEOD\/E-GEOD-10522\/E-GEOD-10522.raw.1.zip\/GSM265854.CEL","comment":{"name":"ArrayExpress FTP file","value":"ftp:\/\/ftp.ebi.ac.uk\/pub\/databases\/microarray\/data\/experiment\/GEOD\/E-GEOD-10522\/E-GEOD-10522.raw.1.zip"}},{"type":"derived data matrix","name":"E-GEOD-10522-processed-data-1605344270.txt","url":"ftp:\/\/ftp.ebi.ac.uk\/pub\/databases\/microarray\/data\/experiment\/GEOD\/E-GEOD-10522\/E-GEOD-10522.processed.1.zip\/E-GEOD-10522-processed-data-1605344270.txt","comment":{"name":"Derived ArrayExpress FTP file","value":"ftp:\/\/ftp.ebi.ac.uk\/pub\/databases\/microarray\/data\/experiment\/GEOD\/E-GEOD-10522\/E-GEOD-10522.processed.1.zip"}}],"labeled-extract":{"name":"GSE10522GSM265854 LE","label":"biotin"},"scan":{"name":"long 14A"},"source":{"name":"GSE10522GSM265854"},"variable":[{"name":"TREATMENT TIME","value":78,"unit":"hours"},{"name":"TEMPERATURE","value":14,"unit":"degree_C"}]},{"assay":{"name":"short 17B"},"characteristic":[{"category":"Organism","value":"Arabidopsis thaliana"},{"category":"Age","value":"4-5","unit":"weeks"},{"category":"OrganismPart","value":"rosette"},{"category":"Ecotype","value":"Col-0"}],"extract":{"name":"GSE10522GSM265859 extract"},"file":[{"type":"data","name":"GSM265859.CEL","url":"ftp:\/\/ftp.ebi.ac.uk\/pub\/databases\/microarray\/data\/experiment\/GEOD\/E-GEOD-10522\/E-GEOD-10522.raw.1.zip\/GSM265859.CEL","comment":{"name":"ArrayExpress FTP file","value":"ftp:\/\/ftp.ebi.ac.uk\/pub\/databases\/microarray\/data\/experiment\/GEOD\/E-GEOD-10522\/E-GEOD-10522.raw.1.zip"}},{"type":"derived data matrix","name":"E-GEOD-10522-processed-data-1605344270.txt","url":"ftp:\/\/ftp.ebi.ac.uk\/pub\/databases\/microarray\/data\/experiment\/GEOD\/E-GEOD-10522\/E-GEOD-10522.processed.1.zip\/E-GEOD-10522-processed-data-1605344270.txt","comment":{"name":"Derived ArrayExpress FTP file","value":"ftp:\/\/ftp.ebi.ac.uk\/pub\/databases\/microarray\/data\/experiment\/GEOD\/E-GEOD-10522\/E-GEOD-10522.processed.1.zip"}}],"labeled-extract":{"name":"GSE10522GSM265859 LE","label":"biotin"},"scan":{"name":"short 17B"},"source":{"name":"GSE10522GSM265859"},"variable":[{"name":"TREATMENT TIME","value":6,"unit":"hours"},{"name":"TEMPERATURE","value":17,"unit":"degree_C"}]},{"assay":{"name":"short 17A"},"characteristic":[{"category":"Organism","value":"Arabidopsis thaliana"},{"category":"Age","value":"4-5","unit":"weeks"},{"category":"OrganismPart","value":"rosette"},{"category":"Ecotype","value":"Col-0"}],"extract":{"name":"GSE10522GSM265847 extract"},"file":[{"type":"data","name":"GSM265847.CEL","url":"ftp:\/\/ftp.ebi.ac.uk\/pub\/databases\/microarray\/data\/experiment\/GEOD\/E-GEOD-10522\/E-GEOD-10522.raw.1.zip\/GSM265847.CEL","comment":{"name":"ArrayExpress FTP file","value":"ftp:\/\/ftp.ebi.ac.uk\/pub\/databases\/microarray\/data\/experiment\/GEOD\/E-GEOD-10522\/E-GEOD-10522.raw.1.zip"}},{"type":"derived data matrix","name":"E-GEOD-10522-processed-data-1605344270.txt","url":"ftp:\/\/ftp.ebi.ac.uk\/pub\/databases\/microarray\/data\/experiment\/GEOD\/E-GEOD-10522\/E-GEOD-10522.processed.1.zip\/E-GEOD-10522-processed-data-1605344270.txt","comment":{"name":"Derived ArrayExpress FTP file","value":"ftp:\/\/ftp.ebi.ac.uk\/pub\/databases\/microarray\/data\/experiment\/GEOD\/E-GEOD-10522\/E-GEOD-10522.processed.1.zip"}}],"labeled-extract":{"name":"GSE10522GSM265847 LE","label":"biotin"},"scan":{"name":"short 17A"},"source":{"name":"GSE10522GSM265847"},"variable":[{"name":"TREATMENT TIME","value":6,"unit":"hours"},{"name":"TEMPERATURE","value":17,"unit":"degree_C"}]},{"assay":{"name":"long 17B"},"characteristic":[{"category":"Organism","value":"Arabidopsis thaliana"},{"category":"Age","value":"4-5","unit":"weeks"},{"category":"OrganismPart","value":"rosette"},{"category":"Ecotype","value":"Col-0"}],"extract":{"name":"GSE10522GSM265865 extract"},"file":[{"type":"data","name":"GSM265865.CEL","url":"ftp:\/\/ftp.ebi.ac.uk\/pub\/databases\/microarray\/data\/experiment\/GEOD\/E-GEOD-10522\/E-GEOD-10522.raw.1.zip\/GSM265865.CEL","comment":{"name":"ArrayExpress FTP file","value":"ftp:\/\/ftp.ebi.ac.uk\/pub\/databases\/microarray\/data\/experiment\/GEOD\/E-GEOD-10522\/E-GEOD-10522.raw.1.zip"}},{"type":"derived data matrix","name":"E-GEOD-10522-processed-data-1605344270.txt","url":"ftp:\/\/ftp.ebi.ac.uk\/pub\/databases\/microarray\/data\/experiment\/GEOD\/E-GEOD-10522\/E-GEOD-10522.processed.1.zip\/E-GEOD-10522-processed-data-1605344270.txt","comment":{"name":"Derived ArrayExpress FTP file","value":"ftp:\/\/ftp.ebi.ac.uk\/pub\/databases\/microarray\/data\/experiment\/GEOD\/E-GEOD-10522\/E-GEOD-10522.processed.1.zip"}}],"labeled-extract":{"name":"GSE10522GSM265865 LE","label":"biotin"},"scan":{"name":"long 17B"},"source":{"name":"GSE10522GSM265865"},"variable":[{"name":"TREATMENT TIME","value":78,"unit":"hours"},{"name":"TEMPERATURE","value":17,"unit":"degree_C"}]},{"assay":{"name":"long 17A"},"characteristic":[{"category":"Organism","value":"Arabidopsis thaliana"},{"category":"Age","value":"4-5","unit":"weeks"},{"category":"OrganismPart","value":"rosette"},{"category":"Ecotype","value":"Col-0"}],"extract":{"name":"GSE10522GSM265853 extract"},"file":[{"type":"data","name":"GSM265853.CEL","url":"ftp:\/\/ftp.ebi.ac.uk\/pub\/databases\/microarray\/data\/experiment\/GEOD\/E-GEOD-10522\/E-GEOD-10522.raw.1.zip\/GSM265853.CEL","comment":{"name":"ArrayExpress FTP file","value":"ftp:\/\/ftp.ebi.ac.uk\/pub\/databases\/microarray\/data\/experiment\/GEOD\/E-GEOD-10522\/E-GEOD-10522.raw.1.zip"}},{"type":"derived data matrix","name":"E-GEOD-10522-processed-data-1605344270.txt","url":"ftp:\/\/ftp.ebi.ac.uk\/pub\/databases\/microarray\/data\/experiment\/GEOD\/E-GEOD-10522\/E-GEOD-10522.processed.1.zip\/E-GEOD-10522-processed-data-1605344270.txt","comment":{"name":"Derived ArrayExpress FTP file","value":"ftp:\/\/ftp.ebi.ac.uk\/pub\/databases\/microarray\/data\/experiment\/GEOD\/E-GEOD-10522\/E-GEOD-10522.processed.1.zip"}}],"labeled-extract":{"name":"GSE10522GSM265853 LE","label":"biotin"},"scan":{"name":"long 17A"},"source":{"name":"GSE10522GSM265853"},"variable":[{"name":"TREATMENT TIME","value":78,"unit":"hours"},{"name":"TEMPERATURE","value":17,"unit":"degree_C"}]},{"assay":{"name":"control shortA"},"characteristic":[{"category":"Organism","value":"Arabidopsis thaliana"},{"category":"Age","value":"4-5","unit":"weeks"},{"category":"OrganismPart","value":"rosette"},{"category":"Ecotype","value":"Col-0"}],"extract":{"name":"GSE10522GSM265846 extract"},"file":[{"type":"data","name":"GSM265846.CEL","url":"ftp:\/\/ftp.ebi.ac.uk\/pub\/databases\/microarray\/data\/experiment\/GEOD\/E-GEOD-10522\/E-GEOD-10522.raw.1.zip\/GSM265846.CEL","comment":{"name":"ArrayExpress FTP file","value":"ftp:\/\/ftp.ebi.ac.uk\/pub\/databases\/microarray\/data\/experiment\/GEOD\/E-GEOD-10522\/E-GEOD-10522.raw.1.zip"}},{"type":"derived data matrix","name":"E-GEOD-10522-processed-data-1605344270.txt","url":"ftp:\/\/ftp.ebi.ac.uk\/pub\/databases\/microarray\/data\/experiment\/GEOD\/E-GEOD-10522\/E-GEOD-10522.processed.1.zip\/E-GEOD-10522-processed-data-1605344270.txt","comment":{"name":"Derived ArrayExpress FTP file","value":"ftp:\/\/ftp.ebi.ac.uk\/pub\/databases\/microarray\/data\/experiment\/GEOD\/E-GEOD-10522\/E-GEOD-10522.processed.1.zip"}}],"labeled-extract":{"name":"GSE10522GSM265846 LE","label":"biotin"},"scan":{"name":"control shortA"},"source":{"name":"GSE10522GSM265846"},"variable":[{"name":"TREATMENT TIME","value":6,"unit":"hours"},{"name":"TEMPERATURE","value":20,"unit":"degree_C"}]},{"assay":{"name":"control longA"},"characteristic":[{"category":"Organism","value":"Arabidopsis thaliana"},{"category":"Age","value":"4-5","unit":"weeks"},{"category":"OrganismPart","value":"rosette"},{"category":"Ecotype","value":"Col-0"}],"extract":{"name":"GSE10522GSM265852 extract"},"file":[{"type":"data","name":"GSM265852.CEL","url":"ftp:\/\/ftp.ebi.ac.uk\/pub\/databases\/microarray\/data\/experiment\/GEOD\/E-GEOD-10522\/E-GEOD-10522.raw.1.zip\/GSM265852.CEL","comment":{"name":"ArrayExpress FTP file","value":"ftp:\/\/ftp.ebi.ac.uk\/pub\/databases\/microarray\/data\/experiment\/GEOD\/E-GEOD-10522\/E-GEOD-10522.raw.1.zip"}},{"type":"derived data matrix","name":"E-GEOD-10522-processed-data-1605344270.txt","url":"ftp:\/\/ftp.ebi.ac.uk\/pub\/databases\/microarray\/data\/experiment\/GEOD\/E-GEOD-10522\/E-GEOD-10522.processed.1.zip\/E-GEOD-10522-processed-data-1605344270.txt","comment":{"name":"Derived ArrayExpress FTP file","value":"ftp:\/\/ftp.ebi.ac.uk\/pub\/databases\/microarray\/data\/experiment\/GEOD\/E-GEOD-10522\/E-GEOD-10522.processed.1.zip"}}],"labeled-extract":{"name":"GSE10522GSM265852 LE","label":"biotin"},"scan":{"name":"control longA"},"source":{"name":"GSE10522GSM265852"},"variable":[{"name":"TREATMENT TIME","value":78,"unit":"hours"},{"name":"TEMPERATURE","value":20,"unit":"degree_C"}]},{"assay":{"name":"control shortB"},"characteristic":[{"category":"Organism","value":"Arabidopsis thaliana"},{"category":"Age","value":"4-5","unit":"weeks"},{"category":"OrganismPart","value":"rosette"},{"category":"Ecotype","value":"Col-0"}],"extract":{"name":"GSE10522GSM265858 extract"},"file":[{"type":"data","name":"GSM265858.CEL","url":"ftp:\/\/ftp.ebi.ac.uk\/pub\/databases\/microarray\/data\/experiment\/GEOD\/E-GEOD-10522\/E-GEOD-10522.raw.1.zip\/GSM265858.CEL","comment":{"name":"ArrayExpress FTP file","value":"ftp:\/\/ftp.ebi.ac.uk\/pub\/databases\/microarray\/data\/experiment\/GEOD\/E-GEOD-10522\/E-GEOD-10522.raw.1.zip"}},{"type":"derived data matrix","name":"E-GEOD-10522-processed-data-1605344270.txt","url":"ftp:\/\/ftp.ebi.ac.uk\/pub\/databases\/microarray\/data\/experiment\/GEOD\/E-GEOD-10522\/E-GEOD-10522.processed.1.zip\/E-GEOD-10522-processed-data-1605344270.txt","comment":{"name":"Derived ArrayExpress FTP file","value":"ftp:\/\/ftp.ebi.ac.uk\/pub\/databases\/microarray\/data\/experiment\/GEOD\/E-GEOD-10522\/E-GEOD-10522.processed.1.zip"}}],"labeled-extract":{"name":"GSE10522GSM265858 LE","label":"biotin"},"scan":{"name":"control shortB"},"source":{"name":"GSE10522GSM265858"},"variable":[{"name":"TREATMENT TIME","value":6,"unit":"hours"},{"name":"TEMPERATURE","value":20,"unit":"degree_C"}]},{"assay":{"name":"control longB"},"characteristic":[{"category":"Organism","value":"Arabidopsis thaliana"},{"category":"Age","value":"4-5","unit":"weeks"},{"category":"OrganismPart","value":"rosette"},{"category":"Ecotype","value":"Col-0"}],"extract":{"name":"GSE10522GSM265864 extract"},"file":[{"type":"data","name":"GSM265864.CEL","url":"ftp:\/\/ftp.ebi.ac.uk\/pub\/databases\/microarray\/data\/experiment\/GEOD\/E-GEOD-10522\/E-GEOD-10522.raw.1.zip\/GSM265864.CEL","comment":{"name":"ArrayExpress FTP file","value":"ftp:\/\/ftp.ebi.ac.uk\/pub\/databases\/microarray\/data\/experiment\/GEOD\/E-GEOD-10522\/E-GEOD-10522.raw.1.zip"}},{"type":"derived data matrix","name":"E-GEOD-10522-processed-data-1605344270.txt","url":"ftp:\/\/ftp.ebi.ac.uk\/pub\/databases\/microarray\/data\/experiment\/GEOD\/E-GEOD-10522\/E-GEOD-10522.processed.1.zip\/E-GEOD-10522-processed-data-1605344270.txt","comment":{"name":"Derived ArrayExpress FTP file","value":"ftp:\/\/ftp.ebi.ac.uk\/pub\/databases\/microarray\/data\/experiment\/GEOD\/E-GEOD-10522\/E-GEOD-10522.processed.1.zip"}}],"labeled-extract":{"name":"GSE10522GSM265864 LE","label":"biotin"},"scan":{"name":"control longB"},"source":{"name":"GSE10522GSM265864"},"variable":[{"name":"TREATMENT TIME","value":78,"unit":"hours"},{"name":"TEMPERATURE","value":20,"unit":"degree_C"}]},{"assay":{"name":"short 8B"},"characteristic":[{"category":"Organism","value":"Arabidopsis thaliana"},{"category":"Age","value":"4-5","unit":"weeks"},{"category":"OrganismPart","value":"rosette"},{"category":"Ecotype","value":"Col-0"}],"extract":{"name":"GSE10522GSM265863 extract"},"file":[{"type":"data","name":"GSM265863.CEL","url":"ftp:\/\/ftp.ebi.ac.uk\/pub\/databases\/microarray\/data\/experiment\/GEOD\/E-GEOD-10522\/E-GEOD-10522.raw.1.zip\/GSM265863.CEL","comment":{"name":"ArrayExpress FTP file","value":"ftp:\/\/ftp.ebi.ac.uk\/pub\/databases\/microarray\/data\/experiment\/GEOD\/E-GEOD-10522\/E-GEOD-10522.raw.1.zip"}},{"type":"derived data matrix","name":"E-GEOD-10522-processed-data-1605344270.txt","url":"ftp:\/\/ftp.ebi.ac.uk\/pub\/databases\/microarray\/data\/experiment\/GEOD\/E-GEOD-10522\/E-GEOD-10522.processed.1.zip\/E-GEOD-10522-processed-data-1605344270.txt","comment":{"name":"Derived ArrayExpress FTP file","value":"ftp:\/\/ftp.ebi.ac.uk\/pub\/databases\/microarray\/data\/experiment\/GEOD\/E-GEOD-10522\/E-GEOD-10522.processed.1.zip"}}],"labeled-extract":{"name":"GSE10522GSM265863 LE","label":"biotin"},"scan":{"name":"short 8B"},"source":{"name":"GSE10522GSM265863"},"variable":[{"name":"TREATMENT TIME","value":6,"unit":"hours"},{"name":"TEMPERATURE","value":8,"unit":"degree_C"}]},{"assay":{"name":"short 8A"},"characteristic":[{"category":"Organism","value":"Arabidopsis thaliana"},{"category":"Age","value":"4-5","unit":"weeks"},{"category":"OrganismPart","value":"rosette"},{"category":"Ecotype","value":"Col-0"}],"extract":{"name":"GSE10522GSM265851 extract"},"file":[{"type":"data","name":"GSM265851.CEL","url":"ftp:\/\/ftp.ebi.ac.uk\/pub\/databases\/microarray\/data\/experiment\/GEOD\/E-GEOD-10522\/E-GEOD-10522.raw.1.zip\/GSM265851.CEL","comment":{"name":"ArrayExpress FTP file","value":"ftp:\/\/ftp.ebi.ac.uk\/pub\/databases\/microarray\/data\/experiment\/GEOD\/E-GEOD-10522\/E-GEOD-10522.raw.1.zip"}},{"type":"derived data matrix","name":"E-GEOD-10522-processed-data-1605344270.txt","url":"ftp:\/\/ftp.ebi.ac.uk\/pub\/databases\/microarray\/data\/experiment\/GEOD\/E-GEOD-10522\/E-GEOD-10522.processed.1.zip\/E-GEOD-10522-processed-data-1605344270.txt","comment":{"name":"Derived ArrayExpress FTP file","value":"ftp:\/\/ftp.ebi.ac.uk\/pub\/databases\/microarray\/data\/experiment\/GEOD\/E-GEOD-10522\/E-GEOD-10522.processed.1.zip"}}],"labeled-extract":{"name":"GSE10522GSM265851 LE","label":"biotin"},"scan":{"name":"short 8A"},"source":{"name":"GSE10522GSM265851"},"variable":[{"name":"TREATMENT TIME","value":6,"unit":"hours"},{"name":"TEMPERATURE","value":8,"unit":"degree_C"}]},{"assay":{"name":"long 8A"},"characteristic":[{"category":"Organism","value":"Arabidopsis thaliana"},{"category":"Age","value":"4-5","unit":"weeks"},{"category":"OrganismPart","value":"rosette"},{"category":"Ecotype","value":"Col-0"}],"extract":{"name":"GSE10522GSM265857 extract"},"file":[{"type":"data","name":"GSM265857.CEL","url":"ftp:\/\/ftp.ebi.ac.uk\/pub\/databases\/microarray\/data\/experiment\/GEOD\/E-GEOD-10522\/E-GEOD-10522.raw.1.zip\/GSM265857.CEL","comment":{"name":"ArrayExpress FTP file","value":"ftp:\/\/ftp.ebi.ac.uk\/pub\/databases\/microarray\/data\/experiment\/GEOD\/E-GEOD-10522\/E-GEOD-10522.raw.1.zip"}},{"type":"derived data matrix","name":"E-GEOD-10522-processed-data-1605344270.txt","url":"ftp:\/\/ftp.ebi.ac.uk\/pub\/databases\/microarray\/data\/experiment\/GEOD\/E-GEOD-10522\/E-GEOD-10522.processed.1.zip\/E-GEOD-10522-processed-data-1605344270.txt","comment":{"name":"Derived ArrayExpress FTP file","value":"ftp:\/\/ftp.ebi.ac.uk\/pub\/databases\/microarray\/data\/experiment\/GEOD\/E-GEOD-10522\/E-GEOD-10522.processed.1.zip"}}],"labeled-extract":{"name":"GSE10522GSM265857 LE","label":"biotin"},"scan":{"name":"long 8A"},"source":{"name":"GSE10522GSM265857"},"variable":[{"name":"TREATMENT TIME","value":78,"unit":"hours"},{"name":"TEMPERATURE","value":8,"unit":"degree_C"}]},{"assay":{"name":"long 8B"},"characteristic":[{"category":"Organism","value":"Arabidopsis thaliana"},{"category":"Age","value":"4-5","unit":"weeks"},{"category":"OrganismPart","value":"rosette"},{"category":"Ecotype","value":"Col-0"}],"extract":{"name":"GSE10522GSM265869 extract"},"file":[{"type":"data","name":"GSM265869.CEL","url":"ftp:\/\/ftp.ebi.ac.uk\/pub\/databases\/microarray\/data\/experiment\/GEOD\/E-GEOD-10522\/E-GEOD-10522.raw.1.zip\/GSM265869.CEL","comment":{"name":"ArrayExpress FTP file","value":"ftp:\/\/ftp.ebi.ac.uk\/pub\/databases\/microarray\/data\/experiment\/GEOD\/E-GEOD-10522\/E-GEOD-10522.raw.1.zip"}},{"type":"derived data matrix","name":"E-GEOD-10522-processed-data-1605344270.txt","url":"ftp:\/\/ftp.ebi.ac.uk\/pub\/databases\/microarray\/data\/experiment\/GEOD\/E-GEOD-10522\/E-GEOD-10522.processed.1.zip\/E-GEOD-10522-processed-data-1605344270.txt","comment":{"name":"Derived ArrayExpress FTP file","value":"ftp:\/\/ftp.ebi.ac.uk\/pub\/databases\/microarray\/data\/experiment\/GEOD\/E-GEOD-10522\/E-GEOD-10522.processed.1.zip"}}],"labeled-extract":{"name":"GSE10522GSM265869 LE","label":"biotin"},"scan":{"name":"long 8B"},"source":{"name":"GSE10522GSM265869"},"variable":[{"name":"TREATMENT TIME","value":78,"unit":"hours"},{"name":"TEMPERATURE","value":8,"unit":"degree_C"}]}]}}