{"protocols":{"api-version":3,"api-revision":"091015","version":1.0,"revision":"091015","total-protocols":3,"protocol":[{"id":62,"accession":"Affymetrix:Protocol:Hybridization-Unknown","name":"Affymetrix:Protocol:Hybridization-Unknown","text":"Affymetrix Generic Hybridization","type":"hybridization protocol","performer":null,"hardware":null,"software":"MicroArraySuite 5.0","standardpublicprotocol":1},{"id":51,"accession":"P-AFFY-6","name":"P-AFFY-6","text":"Title: Affymetrix CEL analysis. Description:","type":"feature_extraction","performer":null,"hardware":"418 [Affymetrix]","software":"MicroArraySuite 5.0","standardpublicprotocol":1},{"id":440203,"accession":"P-G5623-1","name":"P-G5623-1","text":"At day 16, stress treatment started at 3 hours of light treatment. Salt stress (150 mM NaCl), Group Kudla. NaCl was added to a concentration of 150 mM in the Media. To add NaCl the raft was lifted out. A magnetic stir bar and a stirrer were used to mix the media and the added NaCl. After the rafts were put back in the boxes, they were transferred back to the climate chamber.","type":"specified_biomaterial_action","performer":null,"hardware":null,"software":null,"standardpublicprotocol":null}]}}